geodemo/__init__.py
geodemo/common.py
geodemo/geodemo.py
geodemo/toolbar.py
geodemo/utils.py
geodemo-0.1.0.dist-info/LICENSE
geodemo-0.1.0.dist-info/METADATA
geodemo-0.1.0.dist-info/WHEEL
geodemo-0.1.0.dist-info/dependency_links.txt
geodemo-0.1.0.dist-info/top_level.txt
geodemo-0.1.0.dist-info/RECORD
