Metadata-Version: 2.1
Name: geodemo
Version: 0.1.0
Summary: A Python package for interactive mapping
Home-page: https://github.com/giswqs/geodemo
Author: Qiusheng Wu
Author-email: giswqs@gmail.com
License: MIT license
Keywords: geodemo
Platform: UNKNOWN
Classifier: Development Status :: 2 - Pre-Alpha
Classifier: Intended Audience :: Developers
Classifier: License :: OSI Approved :: MIT License
Classifier: Natural Language :: English
Classifier: Programming Language :: Python :: 3
Classifier: Programming Language :: Python :: 3.5
Classifier: Programming Language :: Python :: 3.6
Classifier: Programming Language :: Python :: 3.7
Classifier: Programming Language :: Python :: 3.8
Requires-Python: >=3.5
Requires-Dist: earthengine-api
Requires-Dist: folium
Requires-Dist: geopandas
Requires-Dist: ipyfilechooser
Requires-Dist: ipyleaflet
Requires-Dist: matplotlib
Requires-Dist: pyshp
Requires-Dist: whitebox (>=1.4.1)
Requires-Dist: whiteboxgui
